[
   {
      "ip":"78.111.111.236",
      "hash":"a95bb896b622556c5567c7256794378a",
      "owner":"ZERO",
   },
   {
      "ip":"91.151.94.127",
      "hash":"a95bb896b622556c5567c7256794378a",
      "owner":"SRP",
   },
   {
      "ip":"217.195.197.221",
      "hash":"535dc5c00bfae6560b67395d16f5e853",
      "owner":"Resul",
   },
   {
      "ip":"91.151.94.89",
      "hash":"535dc5c00bfae6560b67395d16f5e853",
      "owner":"Resul",
   },
   {
      "ip":"188.119.40.151",
      "hash":"4lb4tr0szorTlatmaMlazIm",
      "owner":"Albatros",
   }
]
